ephor_ti/__init__.py
ephor_ti/api_client.py
ephor_ti/api_response.py
ephor_ti/configuration.py
ephor_ti/exceptions.py
ephor_ti/py.typed
ephor_ti/rest.py
ephor_ti/api/__init__.py
ephor_ti/api/account_api.py
ephor_ti/api/background_services_api.py
ephor_ti/api/brain_rot_plus_api.py
ephor_ti/api/channels_api.py
ephor_ti/api/library_api.py
ephor_ti/api/projects_api.py
ephor_ti/api/second_brain_api.py
ephor_ti/models/__init__.py
ephor_ti/models/account.py
ephor_ti/models/artifact.py
ephor_ti/models/attachment.py
ephor_ti/models/body_add_webcrawling_request_api_v1_crawl_new_post.py
ephor_ti/models/channel.py
ephor_ti/models/channel_create.py
ephor_ti/models/channel_message.py
ephor_ti/models/channel_state.py
ephor_ti/models/channel_update.py
ephor_ti/models/collection_item.py
ephor_ti/models/command.py
ephor_ti/models/command_parameter.py
ephor_ti/models/command_step.py
ephor_ti/models/comment.py
ephor_ti/models/conversation_input.py
ephor_ti/models/conversation_output.py
ephor_ti/models/crawl_response.py
ephor_ti/models/create_channel200_response.py
ephor_ti/models/expert_comment.py
ephor_ti/models/http_validation_error.py
ephor_ti/models/ingest_request.py
ephor_ti/models/ingest_response.py
ephor_ti/models/ingest_stats.py
ephor_ti/models/ingest_video_request.py
ephor_ti/models/integration.py
ephor_ti/models/library_input.py
ephor_ti/models/library_item.py
ephor_ti/models/library_output.py
ephor_ti/models/library_response.py
ephor_ti/models/manifest_item.py
ephor_ti/models/message.py
ephor_ti/models/message_expert_summary.py
ephor_ti/models/project_create.py
ephor_ti/models/project_detail_response_input.py
ephor_ti/models/project_detail_response_output.py
ephor_ti/models/project_list_response.py
ephor_ti/models/project_remove_user_response.py
ephor_ti/models/project_response.py
ephor_ti/models/project_update.py
ephor_ti/models/project_with_feed.py
ephor_ti/models/retrieve_request.py
ephor_ti/models/retrieve_response.py
ephor_ti/models/retrieve_result.py
ephor_ti-0.0.1.dist-info/METADATA
ephor_ti-0.0.1.dist-info/WHEEL
ephor_ti-0.0.1.dist-info/top_level.txt
ephor_ti-0.0.1.dist-info/RECORD
